README.md
setup.py
tei_reader/__init__.py
tei_reader/tei_reader.py
tei_reader.egg-info/PKG-INFO
tei_reader.egg-info/SOURCES.txt
tei_reader.egg-info/dependency_links.txt
tei_reader.egg-info/not-zip-safe
tei_reader.egg-info/requires.txt
tei_reader.egg-info/top_level.txt
tei_reader/models/__init__.py
tei_reader/models/attribute.py
tei_reader/models/corpora.py
tei_reader/models/division.py
tei_reader/models/document.py
tei_reader/models/element.py
tei_reader/models/part.py
tei_reader/models/placeholder_attribute.py
tei_reader/models/placeholder_division.py
tei_reader/models/placeholder_element.py
tei_reader/models/placeholder_part.py
tei_reader/models/util.py
tei_reader/transform/tei-content.dtd
tei_reader/transform/tei-transform.xsl