Metadata-Version: 2.1
Name: tei-reader
Version: 0.0.13
Summary: TEI Reader
Home-page: https://github.com/UUDigitalHumanitieslab/tei_reader
Author: Sheean Spoel (Digital Humanities Lab, Utrecht University)
Author-email: s.j.j.spoel@uu.nl
License: MIT
Platform: UNKNOWN
Requires-Python: >=3.6, <4
